optds_io/__init__.py
optds_io/provenance.py
optds_io/py.typed
optds_io-0.1.0.dist-info/METADATA
optds_io-0.1.0.dist-info/WHEEL
optds_io-0.1.0.dist-info/RECORD
