Metadata-Version: 2.4
Name: optds-io
Version: 0.1.0
Summary: The Storage Layer. Handles Parquet/Arrow reads/writes, partitioning logic, and directory structures.
Author-email: Raeid Saqur <raeid.saqur@maths.ox.ac.uk>
Requires-Python: >=3.10
Requires-Dist: optds-core==0.1.0
Requires-Dist: pandas
Requires-Dist: polars
Requires-Dist: pyarrow>=14.0
Provides-Extra: s3
Requires-Dist: s3fs; extra == 's3'
